README.md
setup.cfg
setup.py
ftr_classifier/__build_lemmatizer.py
ftr_classifier/__init__.py
ftr_classifier/classify.py
ftr_classifier/info.py
ftr_classifier/lemma_count.py
ftr_classifier/manage_functions.py
ftr_classifier/models.py
ftr_classifier/word_lists.py
ftr_classifier/data/bibtex.bib
ftr_classifier/data/lemma_map
ftr_classifier/data/meta_data
ftr_classifier2.egg-info/PKG-INFO
ftr_classifier2.egg-info/SOURCES.txt
ftr_classifier2.egg-info/dependency_links.txt
ftr_classifier2.egg-info/requires.txt
ftr_classifier2.egg-info/top_level.txt