Metadata-Version: 2.1
Name: ftr-classifier2
Version: 2.2
Summary: Classifies English, Dutch and German sentences in terms of how they refer to the future.
Home-page: https://github.com/jonaskonig/ftr_classifier.git
Author: cole robertson, Jonas Koenig
Author-email: pypi@jonaskoenig.com
License: MIT
Download-URL: https://github.com/jonaskonig/future_modality/archive/2.2.tar.gz
Platform: UNKNOWN
Requires-Python: >3.6.*
